librepythonista_py_edit/__init__.py
librepythonista_py_edit/cell_edit.py
librepythonista_py_edit/hello.py
librepythonista_py_edit/html/index.html
librepythonista_py_edit/html/css/codemirror.min.css
librepythonista_py_edit/html/css/show-hint.min.css
librepythonista_py_edit/html/css/theme/material-darker.min.css
librepythonista_py_edit/html/css/theme/night.min.css
librepythonista_py_edit/html/js/codemirror.min.js
librepythonista_py_edit/html/js/python.min.js
librepythonista_py_edit/html/js/show-hint.min.js
librepythonista_py_edit/log/__init__.py
librepythonista_py_edit/log/default_logger.py
librepythonista_py_edit/log/logger_config.py
librepythonista_python_editor-0.1.9.dist-info/METADATA
librepythonista_python_editor-0.1.9.dist-info/WHEEL
librepythonista_python_editor-0.1.9.dist-info/entry_points.txt
librepythonista_python_editor-0.1.9.dist-info/licenses/LICENSE
librepythonista_python_editor-0.1.9.dist-info/RECORD
