Metadata-Version: 2.4
Name: librepythonista-python-editor
Version: 0.1.9
Summary: A Python editor for LibreOffice that has the LibrePythonista extension installed.
Project-URL: Homepage, https://github.com/Amourspirit/python-librepythonista-python-editor
Project-URL: Repository, https://github.com/Amourspirit/python-librepythonista-python-editor
Project-URL: Issues, https://github.com/Amourspirit/python-librepythonista-python-editor/issues
Author-email: ":Barry-Thomas-Paul: Moss" <4193389+Amourspirit@users.noreply.github.com>
License: Copyright 2024 :Barry-Thomas-Paul: Moss
License-File: LICENSE
Keywords: LibreOffice,LibrePythonista,extension,ooodev
Classifier: Intended Audience :: Developers
Classifier: License :: OSI Approved :: Apache Software License
Classifier: Programming Language :: Python :: 3
Classifier: Programming Language :: Python :: 3.8
Classifier: Programming Language :: Python :: 3.9
Classifier: Programming Language :: Python :: 3.10
Classifier: Programming Language :: Python :: 3.11
Classifier: Programming Language :: Python :: 3.12
Classifier: Topic :: Software Development :: Build Tools
Requires-Python: >=3.8
Requires-Dist: cefpython3>=66.1; sys_platform == 'win32'
Requires-Dist: jedi>=0.19.0
Requires-Dist: pyobjc>=10.3.1; platform_system == 'darwin'
Requires-Dist: pyqt5>=5.15.4; platform_system == 'linux'
Requires-Dist: pyqt6>=6.7.0; platform_system == 'darwin'
Requires-Dist: pyside2>=5.15.0; platform_system == 'linux'
Requires-Dist: pywebview>=5.3.2
Requires-Dist: qtpy>=2.4.0; platform_system == 'linux'
